sqlalchemy_postgres_autocommit/__init__.py
sqlalchemy_postgres_autocommit/databases.py
sqlalchemy_postgres_autocommit/pytest/__init__.py
sqlalchemy_postgres_autocommit/pytest/factories.py
sqlalchemy_postgres_autocommit-0.4.1.dist-info/DESCRIPTION.rst
sqlalchemy_postgres_autocommit-0.4.1.dist-info/METADATA
sqlalchemy_postgres_autocommit-0.4.1.dist-info/RECORD
sqlalchemy_postgres_autocommit-0.4.1.dist-info/WHEEL
sqlalchemy_postgres_autocommit-0.4.1.dist-info/metadata.json
sqlalchemy_postgres_autocommit-0.4.1.dist-info/top_level.txt
