Metadata-Version: 2.0
Name: sqlalchemy-postgres-autocommit
Version: 0.4.1
Summary: A library to use SQLAlchemy with PostgreSQL in an autocommit mode.
Home-page: https://github.com/socialwifi/sqlalchemy-postgres-autocommit
Author: Jakub Gocławski
Author-email: it@socialwifi.com
License: BSD
Platform: UNKNOWN
Classifier: Development Status :: 5 - Production/Stable
Classifier: Environment :: Console
Classifier: Intended Audience :: Developers
Classifier: License :: OSI Approved :: BSD License
Classifier: Operating System :: OS Independent
Classifier: Programming Language :: Python
Classifier: Programming Language :: Python :: 3
Classifier: Programming Language :: Python :: 3.4
Classifier: Programming Language :: Python :: 3.5
Classifier: Programming Language :: Python :: 3.6
Requires-Dist: SQLAlchemy
Requires-Dist: psycopg2
